[
  {
    "full_name": "Lacy Kasper",
    "phone": 7855090667,
    "email": "lkasper0@hostgator.com",
    "age": 31,
    "experience": 23,
    "yearly_income": 4671.95,
    "has_children": false,
    "license_states": "KS",
    "expiration_date": "2020-11-28",
    "license_number": "ttzibd"
  },
  {
    "full_name": "Val Jakobsson",
    "phone": 9155760463,
    "email": "vjakobsson1@rediff.com",
    "age": 10,
    "experience": 5,
    "yearly_income": 9510.01,
    "has_children": true,
    "license_states": "TX",
    "expiration_date": "2020-12-21",
    "license_number": "wrdbty"
  },
  {
    "full_name": "Marco Dunniom",
    "phone": 8178042468,
    "email": "mdunniom2@aol.com",
    "age": 83,
    "experience": 6,
    "yearly_income": 7343.57,
    "has_children": true,
    "license_states": "TX",
    "expiration_date": "2020-09-18",
    "license_number": "3c5i3t"
  },
  {
    "full_name": "Armando Pouton",
    "phone": 7862209407,
    "email": "apouton3@nasa.gov",
    "age": 88,
    "experience": 9,
    "yearly_income": 3709.34,
    "has_children": false,
    "license_states": "FL",
    "expiration_date": "2020-02-28",
    "license_number": "73uf1x"
  },
  {
    "full_name": "Lilah Barz",
    "phone": 8156841661,
    "email": "lbarz4@meetup.com",
    "age": 63,
    "experience": 3,
    "yearly_income": 1570.05,
    "has_children": false,
    "license_states": "IL",
    "expiration_date": "2021-01-31",
    "license_number": "j6z4pt"
  },
  {
    "full_name": "Reid Gellately",
    "phone": 2126927754,
    "email": "rgellately5@nps.gov",
    "age": 65,
    "experience": 12,
    "yearly_income": 6456.83,
    "has_children": false,
    "license_states": "NY",
    "expiration_date": "2020-04-16",
    "license_number": "foatvt"
  },
  {
    "full_name": "Ken Shillum",
    "phone": 9415805880,
    "email": "kshillum6@cmu.edu",
    "age": 99,
    "experience": 23,
    "yearly_income": 7006.61,
    "has_children": false,
    "license_states": "FL",
    "expiration_date": "2020-09-18",
    "license_number": "p84zam"
  },
  {
    "full_name": "Rex Marunchak",
    "phone": 3156597810,
    "email": "rmarunchak7@answers.com",
    "age": 68,
    "experience": 8,
    "yearly_income": 4302.6,
    "has_children": false,
    "license_states": "NY",
    "expiration_date": "2020-10-27",
    "license_number": "bxcy35"
  },
  {
    "full_name": "Luella Loker",
    "phone": 6464764965,
    "email": "lloker8@topsy.com",
    "age": 14,
    "experience": 27,
    "yearly_income": 4046.46,
    "has_children": true,
    "license_states": "NY",
    "expiration_date": "2021-01-16",
    "license_number": "1bc6ia"
  },
  {
    "full_name": "Daffy Beers",
    "phone": 6025173345,
    "email": "dbeers9@opensource.org",
    "age": 89,
    "experience": 21,
    "yearly_income": 289.46,
    "has_children": false,
    "license_states": "AZ",
    "expiration_date": "2020-09-09",
    "license_number": "bsecvy"
  },
  {
    "full_name": "Zonda Merriton",
    "phone": 9377345092,
    "email": "zmerritona@cbc.ca",
    "age": 28,
    "experience": 10,
    "yearly_income": 7984.63,
    "has_children": false,
    "license_states": "OH",
    "expiration_date": "2020-09-14",
    "license_number": "hvkezm"
  },
  {
    "full_name": "Demott Harlin",
    "phone": 7754370352,
    "email": "dharlinb@sitemeter.com",
    "age": 3,
    "experience": 26,
    "yearly_income": 8687.17,
    "has_children": true,
    "license_states": "NV",
    "expiration_date": "2020-10-27",
    "license_number": "wesfj3"
  },
  {
    "full_name": "Gertruda Grimmert",
    "phone": 9041618032,
    "email": "ggrimmertc@1und1.de",
    "age": 3,
    "experience": 15,
    "yearly_income": 4839.89,
    "has_children": true,
    "license_states": "FL",
    "expiration_date": "2020-12-24",
    "license_number": "ifah7q"
  },
  {
    "full_name": "Sherman Cockman",
    "phone": 9722919566,
    "email": "scockmand@163.com",
    "age": 14,
    "experience": 24,
    "yearly_income": 170.28,
    "has_children": true,
    "license_states": "TX",
    "expiration_date": "2020-06-16",
    "license_number": "iv3z1w"
  },
  {
    "full_name": "Karlene Bourdas",
    "phone": 3092982125,
    "email": "kbourdase@1688.com",
    "age": 55,
    "experience": 12,
    "yearly_income": 3363.43,
    "has_children": true,
    "license_states": "IL",
    "expiration_date": "2020-09-25",
    "license_number": "nevwyc"
  },
  {
    "full_name": "Duke Syversen",
    "phone": 8159134012,
    "email": "dsyversenf@blogs.com",
    "age": 63,
    "experience": 27,
    "yearly_income": 8853.49,
    "has_children": true,
    "license_states": "IL",
    "expiration_date": "2020-10-02",
    "license_number": "g6s8ux"
  },
  {
    "full_name": "Debbi Costa",
    "phone": 9523652790,
    "email": "dcostag@chron.com",
    "age": 23,
    "experience": 19,
    "yearly_income": 9483.1,
    "has_children": false,
    "license_states": "MN",
    "expiration_date": "2020-02-22",
    "license_number": "8m07vl"
  },
  {
    "full_name": "Langston Hemms",
    "phone": 9542299801,
    "email": "lhemmsh@amazonaws.com",
    "age": 72,
    "experience": 30,
    "yearly_income": 3737.84,
    "has_children": false,
    "license_states": "FL",
    "expiration_date": "2020-08-13",
    "license_number": "iiy7hm"
  },
  {
    "full_name": "Kaleb Grunguer",
    "phone": 9146314402,
    "email": "kgrungueri@wix.com",
    "age": 66,
    "experience": 19,
    "yearly_income": 1829.6,
    "has_children": true,
    "license_states": "NY",
    "expiration_date": "2020-11-20",
    "license_number": "i0wgtw"
  },
  {
    "full_name": "Levi O'Dowd",
    "phone": 9519160938,
    "email": "lodowdj@whitehouse.gov",
    "age": 17,
    "experience": 7,
    "yearly_income": 5575.84,
    "has_children": false,
    "license_states": "CA",
    "expiration_date": "2020-03-13",
    "license_number": "r5vdev"
  },
  {
    "full_name": "Hansiain Aldersea",
    "phone": 8596788016,
    "email": "halderseak@lycos.com",
    "age": 61,
    "experience": 25,
    "yearly_income": 4111.31,
    "has_children": false,
    "license_states": "KY",
    "expiration_date": "2020-08-28",
    "license_number": "jlupu1"
  },
  {
    "full_name": "Hendrik Warmington",
    "phone": 4075773818,
    "email": "hwarmingtonl@freewebs.com",
    "age": 100,
    "experience": 26,
    "yearly_income": 148.38,
    "has_children": false,
    "license_states": "FL",
    "expiration_date": "2020-08-04",
    "license_number": "5brbcp"
  },
  {
    "full_name": "Hebert Looker",
    "phone": 4053072735,
    "email": "hlookerm@earthlink.net",
    "age": 51,
    "experience": 19,
    "yearly_income": 2080.61,
    "has_children": false,
    "license_states": "OK",
    "expiration_date": "2020-11-28",
    "license_number": "4833ea"
  },
  {
    "full_name": "Sandy Orpen",
    "phone": 9189760213,
    "email": "sorpenn@oracle.com",
    "age": 98,
    "experience": 4,
    "yearly_income": 2955.24,
    "has_children": false,
    "license_states": "OK",
    "expiration_date": "2020-05-31",
    "license_number": "dt1378"
  },
  {
    "full_name": "Klarika Phillcock",
    "phone": 8036482363,
    "email": "kphillcocko@webmd.com",
    "age": 64,
    "experience": 19,
    "yearly_income": 3410.72,
    "has_children": false,
    "license_states": "SC",
    "expiration_date": "2020-04-10",
    "license_number": "5br5bj"
  },
  {
    "full_name": "Ellissa Horsefield",
    "phone": 6095411737,
    "email": "ehorsefieldp@ycombinator.com",
    "age": 44,
    "experience": 9,
    "yearly_income": 6321.12,
    "has_children": true,
    "license_states": "NJ",
    "expiration_date": "2020-06-28",
    "license_number": "06wvp7"
  },
  {
    "full_name": "Jaymee Reichartz",
    "phone": 2027171428,
    "email": "jreichartzq@newyorker.com",
    "age": 68,
    "experience": 17,
    "yearly_income": 7786.93,
    "has_children": true,
    "license_states": "DC",
    "expiration_date": "2020-12-24",
    "license_number": "ywzz26"
  },
  {
    "full_name": "Jarred Plom",
    "phone": 8127699571,
    "email": "jplomr@goo.gl",
    "age": 97,
    "experience": 8,
    "yearly_income": 3431.52,
    "has_children": false,
    "license_states": "IN",
    "expiration_date": "2020-05-09",
    "license_number": "l51v3q"
  },
  {
    "full_name": "Radcliffe Langston",
    "phone": 6145804195,
    "email": "rlangstons@livejournal.com",
    "age": 87,
    "experience": 11,
    "yearly_income": 9052.93,
    "has_children": true,
    "license_states": "OH",
    "expiration_date": "2020-06-27",
    "license_number": "682gbt"
  },
  {
    "full_name": "Sammie Filinkov",
    "phone": 5132978485,
    "email": "sfilinkovt@yolasite.com",
    "age": 19,
    "experience": 27,
    "yearly_income": 8992.8,
    "has_children": true,
    "license_states": "OH",
    "expiration_date": "2020-07-07",
    "license_number": "dv9n3q"
  },
  {
    "full_name": "Marigold Barti",
    "phone": 5407954968,
    "email": "mbartiu@hostgator.com",
    "age": 28,
    "experience": 1,
    "yearly_income": 3271.38,
    "has_children": false,
    "license_states": "VA",
    "expiration_date": "2020-03-13",
    "license_number": "er4tca"
  },
  {
    "full_name": "Carol-jean Barensky",
    "phone": 2129413546,
    "email": "cbarenskyv@uiuc.edu",
    "age": 86,
    "experience": 17,
    "yearly_income": 2332.4,
    "has_children": false,
    "license_states": "NY",
    "expiration_date": "2020-10-25",
    "license_number": "imebzl"
  },
  {
    "full_name": "Lindie Valentin",
    "phone": 5598749322,
    "email": "lvalentinw@redcross.org",
    "age": 60,
    "experience": 10,
    "yearly_income": 7948.32,
    "has_children": false,
    "license_states": "CA",
    "expiration_date": "2020-05-17",
    "license_number": "xaff8b"
  },
  {
    "full_name": "Alyss Becerro",
    "phone": 2121972044,
    "email": "abecerrox@so-net.ne.jp",
    "age": 43,
    "experience": 19,
    "yearly_income": 7795.73,
    "has_children": true,
    "license_states": "NY",
    "expiration_date": "2020-06-15",
    "license_number": "qwil5m"
  },
  {
    "full_name": "Meara Vigors",
    "phone": 2093237697,
    "email": "mvigorsy@phoca.cz",
    "age": 43,
    "experience": 2,
    "yearly_income": 2114.25,
    "has_children": false,
    "license_states": "CA",
    "expiration_date": "2020-11-15",
    "license_number": "ckb9ht"
  },
  {
    "full_name": "Avie Garard",
    "phone": 2121615434,
    "email": "agarardz@istockphoto.com",
    "age": 44,
    "experience": 7,
    "yearly_income": 9709.09,
    "has_children": false,
    "license_states": "NY",
    "expiration_date": "2020-04-02",
    "license_number": "sq6yk4"
  },
  {
    "full_name": "Lita Mc Caughen",
    "phone": 6123991903,
    "email": "lmc10@unc.edu",
    "age": 26,
    "experience": 6,
    "yearly_income": 7483.06,
    "has_children": true,
    "license_states": "MN",
    "expiration_date": "2020-06-15",
    "license_number": "fjfz19"
  },
  {
    "full_name": "Frannie Popelay",
    "phone": 4109209474,
    "email": "fpopelay11@tinypic.com",
    "age": 22,
    "experience": 18,
    "yearly_income": 2460.89,
    "has_children": true,
    "license_states": "MD",
    "expiration_date": "2020-09-25",
    "license_number": "a7vhx2"
  },
  {
    "full_name": "Humfried Dare",
    "phone": 2392621627,
    "email": "hdare12@census.gov",
    "age": 16,
    "experience": 8,
    "yearly_income": 8622.46,
    "has_children": true,
    "license_states": "FL",
    "expiration_date": "2020-12-20",
    "license_number": "y9oddu"
  },
  {
    "full_name": "Roxie Kubicek",
    "phone": 2125006250,
    "email": "rkubicek13@bing.com",
    "age": 89,
    "experience": 22,
    "yearly_income": 5094.23,
    "has_children": true,
    "license_states": "NY",
    "expiration_date": "2020-09-09",
    "license_number": "f0rbv8"
  },
  {
    "full_name": "Helge Kleingrub",
    "phone": 5732122582,
    "email": "hkleingrub14@oracle.com",
    "age": 26,
    "experience": 2,
    "yearly_income": 6929.91,
    "has_children": false,
    "license_states": "MO",
    "expiration_date": "2020-10-28",
    "license_number": "sgz86w"
  },
  {
    "full_name": "Pen Krzyzaniak",
    "phone": 5596703640,
    "email": "pkrzyzaniak15@springer.com",
    "age": 49,
    "experience": 11,
    "yearly_income": 437.47,
    "has_children": false,
    "license_states": "CA",
    "expiration_date": "2021-01-10",
    "license_number": "r5ny8t"
  },
  {
    "full_name": "Delcine Wadeson",
    "phone": 2136356630,
    "email": "dwadeson16@ca.gov",
    "age": 95,
    "experience": 14,
    "yearly_income": 1159.46,
    "has_children": false,
    "license_states": "CA",
    "expiration_date": "2020-11-01",
    "license_number": "w0v8xm"
  },
  {
    "full_name": "Fields Esland",
    "phone": 8039016748,
    "email": "fesland17@goo.ne.jp",
    "age": 74,
    "experience": 19,
    "yearly_income": 8314.06,
    "has_children": true,
    "license_states": "SC",
    "expiration_date": "2021-02-04",
    "license_number": "1262o5"
  },
  {
    "full_name": "Antonella Fransinelli",
    "phone": 7276102771,
    "email": "afransinelli18@hibu.com",
    "age": 70,
    "experience": 5,
    "yearly_income": 9607.25,
    "has_children": false,
    "license_states": "FL",
    "expiration_date": "2020-04-27",
    "license_number": "otb4ph"
  },
  {
    "full_name": "Gloria Whatson",
    "phone": 2055737317,
    "email": "gwhatson19@163.com",
    "age": 31,
    "experience": 25,
    "yearly_income": 3596.74,
    "has_children": true,
    "license_states": "AL",
    "expiration_date": "2020-04-07",
    "license_number": "8robnb"
  },
  {
    "full_name": "Shelden Grelik",
    "phone": 3106497260,
    "email": "sgrelik1a@godaddy.com",
    "age": 18,
    "experience": 23,
    "yearly_income": 9485.98,
    "has_children": true,
    "license_states": "CA",
    "expiration_date": "2020-03-10",
    "license_number": "29t6v0"
  },
  {
    "full_name": "Jules Gunstone",
    "phone": 9107999257,
    "email": "jgunstone1b@amazonaws.com",
    "age": 93,
    "experience": 3,
    "yearly_income": 2704.44,
    "has_children": false,
    "license_states": "NC",
    "expiration_date": "2020-10-08",
    "license_number": "7x5ymw"
  },
  {
    "full_name": "Nappy Hartles",
    "phone": 5039859124,
    "email": "nhartles1c@nytimes.com",
    "age": 24,
    "experience": 26,
    "yearly_income": 2721.72,
    "has_children": false,
    "license_states": "OR",
    "expiration_date": "2020-08-19",
    "license_number": "ut84j6"
  },
  {
    "full_name": "Jason Habert",
    "phone": 3523002531,
    "email": "jhabert1d@mayoclinic.com",
    "age": 59,
    "experience": 9,
    "yearly_income": 6456.87,
    "has_children": true,
    "license_states": "FL",
    "expiration_date": "2021-01-14",
    "license_number": "jut42f"
  },
  {
    "full_name": "Wanda Tesdale",
    "phone": 2167366483,
    "email": "wtesdale1e@multiply.com",
    "age": 81,
    "experience": 7,
    "yearly_income": 4414.51,
    "has_children": false,
    "license_states": "OH",
    "expiration_date": "2020-09-29",
    "license_number": "4xd3t1"
  },
  {
    "full_name": "Jobyna Eastwood",
    "phone": 2025568671,
    "email": "jeastwood1f@constantcontact.com",
    "age": 55,
    "experience": 23,
    "yearly_income": 8868.36,
    "has_children": true,
    "license_states": "DC",
    "expiration_date": "2020-07-04",
    "license_number": "ui9qai"
  },
  {
    "full_name": "Denny Brafferton",
    "phone": 9258781524,
    "email": "dbrafferton1g@dion.ne.jp",
    "age": 55,
    "experience": 25,
    "yearly_income": 6502.26,
    "has_children": false,
    "license_states": "CA",
    "expiration_date": "2020-05-25",
    "license_number": "bez8u1"
  },
  {
    "full_name": "Fern Fullun",
    "phone": 5084523817,
    "email": "ffullun1h@google.co.uk",
    "age": 72,
    "experience": 12,
    "yearly_income": 5935.83,
    "has_children": false,
    "license_states": "MA",
    "expiration_date": "2020-12-10",
    "license_number": "j5phxp"
  },
  {
    "full_name": "Dix McVitty",
    "phone": 5056847585,
    "email": "dmcvitty1i@hubpages.com",
    "age": 10,
    "experience": 12,
    "yearly_income": 6614.25,
    "has_children": true,
    "license_states": "NM",
    "expiration_date": "2020-07-11",
    "license_number": "tc9tyl"
  },
  {
    "full_name": "Trumaine Loraine",
    "phone": 7733865754,
    "email": "tloraine1j@opensource.org",
    "age": 90,
    "experience": 14,
    "yearly_income": 6395.4,
    "has_children": true,
    "license_states": "IL",
    "expiration_date": "2020-07-27",
    "license_number": "sevbz2"
  },
  {
    "full_name": "Huberto Fooks",
    "phone": 3132833539,
    "email": "hfooks1k@toplist.cz",
    "age": 69,
    "experience": 6,
    "yearly_income": 7425.66,
    "has_children": false,
    "license_states": "MI",
    "expiration_date": "2020-04-10",
    "license_number": "kch9s8"
  },
  {
    "full_name": "Frazer Filan",
    "phone": 8034837316,
    "email": "ffilan1l@privacy.gov.au",
    "age": 32,
    "experience": 18,
    "yearly_income": 4014.29,
    "has_children": false,
    "license_states": "SC",
    "expiration_date": "2020-06-19",
    "license_number": "qxasem"
  },
  {
    "full_name": "Vail Emmanuele",
    "phone": 9198111553,
    "email": "vemmanuele1m@oaic.gov.au",
    "age": 76,
    "experience": 12,
    "yearly_income": 3253.17,
    "has_children": false,
    "license_states": "NC",
    "expiration_date": "2020-09-19",
    "license_number": "qy4i1o"
  },
  {
    "full_name": "Rufe Krolman",
    "phone": 4252155279,
    "email": "rkrolman1n@hao123.com",
    "age": 81,
    "experience": 16,
    "yearly_income": 1246.69,
    "has_children": true,
    "license_states": "WA",
    "expiration_date": "2020-11-11",
    "license_number": "wpdpee"
  },
  {
    "full_name": "Minta MacCart",
    "phone": 3017225302,
    "email": "mmaccart1o@loc.gov",
    "age": 59,
    "experience": 21,
    "yearly_income": 7072.97,
    "has_children": true,
    "license_states": "MD",
    "expiration_date": "2020-03-17",
    "license_number": "efdn2q"
  },
  {
    "full_name": "Joyce Firebrace",
    "phone": 5139262264,
    "email": "jfirebrace1p@is.gd",
    "age": 17,
    "experience": 1,
    "yearly_income": 8540.53,
    "has_children": false,
    "license_states": "OH",
    "expiration_date": "2020-11-05",
    "license_number": "28g39s"
  },
  {
    "full_name": "Lottie Casado",
    "phone": 6192420557,
    "email": "lcasado1q@lycos.com",
    "age": 86,
    "experience": 4,
    "yearly_income": 6798.44,
    "has_children": false,
    "license_states": "CA",
    "expiration_date": "2020-06-16",
    "license_number": "jmv37m"
  },
  {
    "full_name": "Tirrell Giberd",
    "phone": 4052474094,
    "email": "tgiberd1r@facebook.com",
    "age": 70,
    "experience": 10,
    "yearly_income": 4662.01,
    "has_children": true,
    "license_states": "OK",
    "expiration_date": "2020-12-01",
    "license_number": "8gzvcg"
  },
  {
    "full_name": "Agata Pautot",
    "phone": 3218116851,
    "email": "apautot1s@youtube.com",
    "age": 30,
    "experience": 12,
    "yearly_income": 5310.29,
    "has_children": true,
    "license_states": "FL",
    "expiration_date": "2020-06-30",
    "license_number": "tz91fg"
  },
  {
    "full_name": "Nikoletta O'Bradain",
    "phone": 3615510092,
    "email": "nobradain1t@loc.gov",
    "age": 77,
    "experience": 2,
    "yearly_income": 1188.59,
    "has_children": false,
    "license_states": "TX",
    "expiration_date": "2020-10-04",
    "license_number": "xg7z2m"
  },
  {
    "full_name": "Adriaens Kasher",
    "phone": 2018492306,
    "email": "akasher1u@marketwatch.com",
    "age": 68,
    "experience": 2,
    "yearly_income": 5396.53,
    "has_children": false,
    "license_states": "NJ",
    "expiration_date": "2020-12-14",
    "license_number": "76wfx2"
  },
  {
    "full_name": "Rebbecca Kaysor",
    "phone": 7199621028,
    "email": "rkaysor1v@tripadvisor.com",
    "age": 93,
    "experience": 3,
    "yearly_income": 3721.41,
    "has_children": false,
    "license_states": "CO",
    "expiration_date": "2020-09-03",
    "license_number": "4lv1jp"
  },
  {
    "full_name": "Cahra Yankishin",
    "phone": 7856408545,
    "email": "cyankishin1w@slideshare.net",
    "age": 98,
    "experience": 25,
    "yearly_income": 5617.68,
    "has_children": true,
    "license_states": "KS",
    "expiration_date": "2021-01-11",
    "license_number": "qdy3fh"
  },
  {
    "full_name": "Brook Tully",
    "phone": 2029334867,
    "email": "btully1x@163.com",
    "age": 45,
    "experience": 22,
    "yearly_income": 945.52,
    "has_children": false,
    "license_states": "DC",
    "expiration_date": "2020-09-06",
    "license_number": "ctw64c"
  },
  {
    "full_name": "Dolley Rawlings",
    "phone": 7136876082,
    "email": "drawlings1y@histats.com",
    "age": 55,
    "experience": 16,
    "yearly_income": 5784.24,
    "has_children": false,
    "license_states": "TX",
    "expiration_date": "2021-02-03",
    "license_number": "f9tw5v"
  },
  {
    "full_name": "Truda Eglington",
    "phone": 7708138142,
    "email": "teglington1z@devhub.com",
    "age": 32,
    "experience": 23,
    "yearly_income": 2097.52,
    "has_children": true,
    "license_states": "GA",
    "expiration_date": "2020-04-11",
    "license_number": "aew06k"
  },
  {
    "full_name": "Dill Olner",
    "phone": 9153992762,
    "email": "dolner20@answers.com",
    "age": 46,
    "experience": 21,
    "yearly_income": 2228.15,
    "has_children": true,
    "license_states": "TX",
    "expiration_date": "2020-07-13",
    "license_number": "qped4y"
  },
  {
    "full_name": "Alex Stoke",
    "phone": 9498852206,
    "email": "astoke21@skype.com",
    "age": 85,
    "experience": 20,
    "yearly_income": 419.03,
    "has_children": true,
    "license_states": "CA",
    "expiration_date": "2020-06-30",
    "license_number": "yuneop"
  },
  {
    "full_name": "Charlton Skelhorn",
    "phone": 8285196371,
    "email": "cskelhorn22@wp.com",
    "age": 55,
    "experience": 9,
    "yearly_income": 1982.22,
    "has_children": false,
    "license_states": "NC",
    "expiration_date": "2020-08-17",
    "license_number": "mz4qw2"
  },
  {
    "full_name": "Kimmie McIlrath",
    "phone": 7136909399,
    "email": "kmcilrath23@census.gov",
    "age": 92,
    "experience": 7,
    "yearly_income": 1951.19,
    "has_children": true,
    "license_states": "TX",
    "expiration_date": "2020-07-20",
    "license_number": "nz842t"
  },
  {
    "full_name": "Clyde Narrie",
    "phone": 2024839060,
    "email": "cnarrie24@people.com.cn",
    "age": 4,
    "experience": 30,
    "yearly_income": 4027.77,
    "has_children": false,
    "license_states": "MD",
    "expiration_date": "2020-12-23",
    "license_number": "3lkfu6"
  },
  {
    "full_name": "Malory Hackford",
    "phone": 7604005730,
    "email": "mhackford25@issuu.com",
    "age": 22,
    "experience": 14,
    "yearly_income": 7541.43,
    "has_children": true,
    "license_states": "CA",
    "expiration_date": "2020-02-18",
    "license_number": "49r682"
  },
  {
    "full_name": "Jenelle Twidale",
    "phone": 3183379608,
    "email": "jtwidale26@sciencedirect.com",
    "age": 75,
    "experience": 5,
    "yearly_income": 1221,
    "has_children": false,
    "license_states": "MA",
    "expiration_date": "2021-01-28",
    "license_number": "0bo1bu"
  },
  {
    "full_name": "Zack Caghy",
    "phone": 7854759526,
    "email": "zcaghy27@list-manage.com",
    "age": 36,
    "experience": 9,
    "yearly_income": 4907.07,
    "has_children": true,
    "license_states": "KS",
    "expiration_date": "2020-07-27",
    "license_number": "efzgrl"
  },
  {
    "full_name": "Lolita Corp",
    "phone": 2561847203,
    "email": "lcorp28@about.me",
    "age": 12,
    "experience": 6,
    "yearly_income": 6449.39,
    "has_children": false,
    "license_states": "AL",
    "expiration_date": "2021-01-25",
    "license_number": "y9zkl9"
  },
  {
    "full_name": "Frieda Macoun",
    "phone": 6198241117,
    "email": "fmacoun29@imgur.com",
    "age": 6,
    "experience": 14,
    "yearly_income": 6356.73,
    "has_children": false,
    "license_states": "CA",
    "expiration_date": "2020-12-11",
    "license_number": "bcnqca"
  },
  {
    "full_name": "Gusta Stanlike",
    "phone": 5098049466,
    "email": "gstanlike2a@a8.net",
    "age": 69,
    "experience": 4,
    "yearly_income": 3189.68,
    "has_children": false,
    "license_states": "WA",
    "expiration_date": "2020-11-03",
    "license_number": "aohdxg"
  },
  {
    "full_name": "Nita Antoniewski",
    "phone": 5593629596,
    "email": "nantoniewski2b@edublogs.org",
    "age": 96,
    "experience": 17,
    "yearly_income": 8822.75,
    "has_children": true,
    "license_states": "CA",
    "expiration_date": "2020-07-12",
    "license_number": "l6ls6t"
  },
  {
    "full_name": "Eilis Kaasmann",
    "phone": 7087202638,
    "email": "ekaasmann2c@paginegialle.it",
    "age": 16,
    "experience": 20,
    "yearly_income": 5983.55,
    "has_children": true,
    "license_states": "IL",
    "expiration_date": "2020-05-17",
    "license_number": "8ds8ak"
  },
  {
    "full_name": "Peggi Joseff",
    "phone": 2127069663,
    "email": "pjoseff2d@engadget.com",
    "age": 25,
    "experience": 16,
    "yearly_income": 8389.79,
    "has_children": true,
    "license_states": "NY",
    "expiration_date": "2020-07-20",
    "license_number": "n5ylxr"
  },
  {
    "full_name": "Elfrida Pond",
    "phone": 6507619857,
    "email": "epond2e@boston.com",
    "age": 2,
    "experience": 18,
    "yearly_income": 9099.65,
    "has_children": true,
    "license_states": "CA",
    "expiration_date": "2021-01-25",
    "license_number": "ui55e0"
  },
  {
    "full_name": "Jeff Mellsop",
    "phone": 7134901070,
    "email": "jmellsop2f@disqus.com",
    "age": 41,
    "experience": 29,
    "yearly_income": 231.31,
    "has_children": true,
    "license_states": "TX",
    "expiration_date": "2020-08-16",
    "license_number": "9dlqbl"
  },
  {
    "full_name": "Queenie Mochan",
    "phone": 8189112784,
    "email": "qmochan2g@netscape.com",
    "age": 46,
    "experience": 8,
    "yearly_income": 9867.18,
    "has_children": true,
    "license_states": "CA",
    "expiration_date": "2020-05-25",
    "license_number": "2rzin2"
  },
  {
    "full_name": "Stu Thorns",
    "phone": 9184357483,
    "email": "sthorns2h@example.com",
    "age": 33,
    "experience": 3,
    "yearly_income": 4743.47,
    "has_children": true,
    "license_states": "OK",
    "expiration_date": "2020-08-26",
    "license_number": "numxfv"
  },
  {
    "full_name": "Bendicty Knightley",
    "phone": 2027299885,
    "email": "bknightley2i@freewebs.com",
    "age": 67,
    "experience": 20,
    "yearly_income": 8222.14,
    "has_children": false,
    "license_states": "DC",
    "expiration_date": "2020-09-13",
    "license_number": "t5nsup"
  },
  {
    "full_name": "Ronnie Harme",
    "phone": 8132159939,
    "email": "rharme2j@netlog.com",
    "age": 74,
    "experience": 3,
    "yearly_income": 1448.54,
    "has_children": false,
    "license_states": "FL",
    "expiration_date": "2020-10-22",
    "license_number": "fxs2gl"
  },
  {
    "full_name": "Vittorio Broadbere",
    "phone": 3344945976,
    "email": "vbroadbere2k@vk.com",
    "age": 26,
    "experience": 27,
    "yearly_income": 429.03,
    "has_children": false,
    "license_states": "AL",
    "expiration_date": "2020-03-01",
    "license_number": "6z7gvx"
  },
  {
    "full_name": "Joe Kunkler",
    "phone": 5598892024,
    "email": "jkunkler2l@alexa.com",
    "age": 1,
    "experience": 23,
    "yearly_income": 8446.87,
    "has_children": true,
    "license_states": "CA",
    "expiration_date": "2020-03-06",
    "license_number": "orsiol"
  },
  {
    "full_name": "Ottilie Vanyushkin",
    "phone": 5853879023,
    "email": "ovanyushkin2m@java.com",
    "age": 35,
    "experience": 3,
    "yearly_income": 732.66,
    "has_children": false,
    "license_states": "NY",
    "expiration_date": "2020-12-26",
    "license_number": "odwkat"
  },
  {
    "full_name": "Amble Bolliver",
    "phone": 7245379110,
    "email": "abolliver2n@wufoo.com",
    "age": 26,
    "experience": 24,
    "yearly_income": 5203.49,
    "has_children": false,
    "license_states": "PA",
    "expiration_date": "2020-10-01",
    "license_number": "8xvh6f"
  },
  {
    "full_name": "Aland Kenneford",
    "phone": 8069580695,
    "email": "akenneford2o@woothemes.com",
    "age": 32,
    "experience": 28,
    "yearly_income": 426.75,
    "has_children": false,
    "license_states": "TX",
    "expiration_date": "2020-11-14",
    "license_number": "6tvln4"
  },
  {
    "full_name": "Kippie Courtney",
    "phone": 2029016132,
    "email": "kcourtney2p@altervista.org",
    "age": 4,
    "experience": 9,
    "yearly_income": 2574.93,
    "has_children": true,
    "license_states": "DC",
    "expiration_date": "2020-07-17",
    "license_number": "hht2s2"
  },
  {
    "full_name": "Nevsa Adriaens",
    "phone": 8164402923,
    "email": "nadriaens2q@naver.com",
    "age": 27,
    "experience": 22,
    "yearly_income": 7614.05,
    "has_children": true,
    "license_states": "MO",
    "expiration_date": "2020-12-19",
    "license_number": "mkobzx"
  },
  {
    "full_name": "Kellina Adderley",
    "phone": 7579950733,
    "email": "kadderley2r@foxnews.com",
    "age": 41,
    "experience": 29,
    "yearly_income": 2561.63,
    "has_children": false,
    "license_states": "VA",
    "expiration_date": "2020-06-07",
    "license_number": "k3d1w9"
  }
]